{
  "id" : {
    "polynomial" : "x^28 + x^27 + x^25 + x^24 + x^23 + x^22 + x^12 + x^10 + x^6 + x^3 + x^2 + x^1 + 1",
    "degree"     : 28,
    "explicit"   : "0x1bc0144f",
    "koopman"    : "0xDE00A27",
    "normal"     : "0xbc0144f"
  },
  "hd" :     [null, null, null,
    /* 3 */ { "bits"    : 268435427, "bytes"   : 33554428 },
    /* 4 */ { "bits"    : 10170, "bytes"   : 1271 },
    /* 5 */ { "bits"    : 1075, "bytes"   : 134 },
    /* 6 */ { "bits"    : 147, "bytes"   : 18 },
    /* 7 */ { "bits"    : 115, "bytes"   : 14 },
    /* 8 */ { "bits"    : 34, "bytes"   : 4 },
    /* 9 */ { "bits"    : 34, "bytes"   : 4 },
    /* 10 */ { "bits"    : 33, "bytes"   : 4 },
    /* 11 */ { "bits"    : 16, "bytes"   : 2 },
    /* 12 */ { "bits"    : 4, "bytes"   : 0 },
    /* 13 */ { "bits"    : 1, "bytes"   : 0 }
  ],
}
