{
  "id" : {
    "polynomial" : "x^28 + x^26 + x^25 + x^23 + x^20 + x^19 + x^18 + x^16 + x^15 + x^12 + x^4 + x^3 + x^2 + x^1 + 1",
    "degree"     : 28,
    "explicit"   : "0x169d901f",
    "koopman"    : "0xb4ec80f",
    "normal"     : "0x69d901f"
  },
  "hd" :     [null, null, null,
    /* 3 */ { "bits"    : 268435427, "bytes"   : 33554428 },
    /* 4 */ { "bits"    : 22683, "bytes"   : 2835 },
    /* 5 */ { "bits"    : 1002, "bytes"   : 125 },
    /* 6 */ { "bits"    : 306, "bytes"   : 38 },
    /* 7 */ { "bits"    : 86, "bytes"   : 10 },
    /* 8 */ { "bits"    : 36, "bytes"   : 4 },
    /* 9 */ { "bits"    : 22, "bytes"   : 2 },
    /* 10 */ { "bits"    : 21, "bytes"   : 2 },
    /* 11 */ { "bits"    : 13, "bytes"   : 1 },
    /* 12 */ { "bits"    : 10, "bytes"   : 1 },
    /* 13 */ { "bits"    : 9, "bytes"   : 1 },
    /* 14 */ { "bits"    : 9, "bytes"   : 1 },
    /* 15 */ { "bits"    : 1, "bytes"   : 0 }
  ],
}
