{
  "identity" : {
    "polynomial" : "x^31 + x^28 + x^26 + x^25 + x^24 + x^23 + x^22 + x^21 + x^19 + x^14 + x^13 + x^12 + x^10 + x^8 + x^7 + x^6 + x^4 + x^1 + 1",
    "degree"     : 31,
    "explicit"   : "0x97E875D3",
    "koopman"    : "0x4BF43AE9",
    "normal"     : "0x17E875D3"
  },
  "profile" : {
    "record" : "# 0x4bf43ae9 HD=3 len=2147483616 Example: Len=2147483617 0x4bf43ae9 {0} (0x40000000) (Bits=2) # 0x4bf43ae9 HD=4 len=68274 Example: Len=68275 0x4bf43ae9 {0,7844} (0x40000000) (Bits=3) # 0x4bf43ae9 HD=5 len=2788 Example: Len=2789 0x4bf43ae9 {0,70,86} (0x40000000) (Bits=4) # 0x4bf43ae9 HD=6 len=1019 Example: Len=1020 0x4bf43ae9 {0,632,839,946} (0x40000000) (Bits=5) # 0x4bf43ae9 HD=7 len=147 Example: Len=148 0x4bf43ae9 {0,29,69} (0x40404000) (Bits=6) # 0x4bf43ae9 HD=8 len=73 Example: Len=74 0x4bf43ae9 {0,10,33,47,55,60} (0x40000000) (Bits=7) # 0x4bf43ae9 HD=9 len=35 Example: Len=36 0x4bf43ae9 {0,10,27,32} (0x40010300) (Bits=8) # 0x4bf43ae9 HD=10 len=21 Example: Len=22 0x4bf43ae9 {0,7,9} (0x4c002003) (Bits=9) # 0x4bf43ae9 HD=11 len=21 Example: Len=22 0x4bf43ae9 {0,7,9} (0x4c002003) (Bits=9) # 0x4bf43ae9 HD=12 len=8 Example: Len=9 0x4bf43ae9 {0,2,3,7,8} (0x4009002c) (Bits=11) # 0x4bf43ae9 HD=13 len=8 Example: Len=9 0x4bf43ae9 {0,2,3,7,8} (0x4009002c) (Bits=11) # 0x4bf43ae9 HD=14 len=8 Example: Len=9 0x4bf43ae9 {0,4} (0x691d0940) (Bits=13) # 0x4bf43ae9 HD=15 len=4 Example: Len=5 0x4bf43ae9 {0,3} (0x54c8f0a0) (Bits=14) # 0x4bf43ae9 HD=16 len=3 Example: Len=4 0x4bf43ae9 {0,1,2} (0x6770a0c0) (Bits=15) # 0x4bf43ae9 HD=17 len=2 Example: Len=3 0x4bf43ae9 {0,1,2} (0x59093453) (Bits=16) # 0x4bf43ae9 HD=18 len=2 Example: Len=3 0x4bf43ae9 {0,1,2} (0x59093453) (Bits=16) # 0x4bf43ae9 HD=19 len=1 Example: Len=2 0x4bf43ae9 {0} (0x6e0e279d) (Bits=18) # 0x4bf43ae9 HD=20 NONE Example: Len=1 0x4bf43ae9 {0} (0x4bf43ae9) (Bits=19) 0x4bf43ae9 {2147483616,68274,2788,1019,147,73,35,21,21,8,8,8,4,3,2,2,1}",
    "HD"     : [null, null, null, 2147483616, 68274,2788,1019,147,73,35,21,21,8,8,8,4,3,2,2,1]
  }
}
